Workbook

Sheet Inputs
A1: 参数 | B1: 数值 | C1: 单位 / 属性 | D1: 来源 / 说明
A2: 股价 | B2: 368.56 | C2: USD；2026-09-08 regular close | D2: S1
A3: 当前股数 | B3: 4.76 | C3: 十亿股；近似数 | D3: S2
A4: Q3 报告自由现金流 | B4: 13.665 | C4: 十亿美元；事实 | D4: S3
A5: Q3 股权薪酬 | B5: 2.019 | C5: 十亿美元；事实 | D5: S3
A6: 要求回报率 | B6: 0.12 | C6: 独立模型假设 | D6: 分析选择
A7: 永续增长率 | B7: 0.04 | C7: 独立模型假设 | D7: 分析选择
A8: TTM 报告 FCF | B8: 39.403 | C8: 十亿美元；四季度相加 | D8: S4
A9: FY2026 调整后 EPS | B9: 11.64 | C9: USD；共识截至 2026-09-07 | D9: S5
A10: Q3 调整后 EPS | B10: 3.32 | C10: USD；事实 | D10: S3
A11: 市值 | B11: =B2*B3 -> 1754.3456 | C11: 十亿美元 | D11: 计算
A12: TTM FCF 倍数 | B12: =B11/B8 -> 44.523148 | C12: 倍 | D12: 计算
A13: TTM FCF 收益率 | B13: =B8/B11 -> 0.022460227 | C13: 比率 | D13: 计算
A14: FY2026 调整后 PE | B14: =B2/B9 -> 31.66323 | C14: 倍 | D14: 计算
A15: Q3 EPS 年化 PE | B15: =B2/(B10*4) -> 27.753012 | C15: 倍；不是年度预测 | D15: 计算
A16: DCF 起始每股经济现金流代理 | B16: =(B4-B5)*4/B3 -> 9.7865546 | C16: USD；季度年化并扣股权薪酬 | D16: 单季年化及固定股数均为限制

Sheet Scenarios
A1: 情景 | B1: AI收入 | C1: 其他收入 | D1: 合计收入 | E1: 调整后净利率 | F1: 稀释股数 | G1: EPS | H1: 期末PE | I1: 一年后价格 | J1: 不含股息回报 | K1: 折现现值
A2: 悲观 | B2: 65 | C2: 50 | D2: =B2+C2 -> 115 | E2: 0.48 | F2: 5 | G2: =D2*E2/F2 -> 11.04 | H2: 22 | I2: =G2*H2 -> 242.88 | J2: =I2/Inputs!B2-1 -> -0.34100282 | K2: =I2/(1+Inputs!B6) -> 216.85714
A3: 基准 | B3: 90 | C3: 54 | D3: =B3+C3 -> 144 | E3: 0.55 | F3: 5 | G3: =D3*E3/F3 -> 15.84 | H3: 30 | I3: =G3*H3 -> 475.2 | J3: =I3/Inputs!B2-1 -> 0.28934231 | K3: =I3/(1+Inputs!B6) -> 424.28571
A4: 乐观 | B4: 115 | C4: 57 | D4: =B4+C4 -> 172 | E4: 0.58 | F4: 5 | G4: =D4*E4/F4 -> 19.952 | H4: 34 | I4: =G4*H4 -> 678.368 | J4: =I4/Inputs!B2-1 -> 0.84059041 | K4: =I4/(1+Inputs!B6) -> 605.68571
A5: 金额为十亿美元，股数为十亿股，EPS和股价为美元。
A6: 所有情景输入均为独立假设；乐观AI收入对齐管理层展望，非保证。
A7: 估值时点约为一年后；无情景概率；不得将目标价当成今天现值。
A8: 基准现值折价 | B8: =1-Inputs!B2/K3 -> 0.13134007
A9: 30倍PE下要求EPS | B9: =Inputs!B2*(1+Inputs!B6)/30 -> 13.759573
A10: 30倍PE下要求AI收入 | B10: =B9*5/0.55-54 -> 71.08703
A11: 25倍PE下要求AI收入 | B11: =Inputs!B2*(1+Inputs!B6)/25*5/0.55-54 -> 96.104436

Sheet DCF
A1: 五年年增长率 | B1: 第1年现金流 | C1: 第2年现金流 | D1: 第3年现金流 | E1: 第4年现金流 | F1: 第5年现金流 | G1: 显式现金流现值 | H1: 第五年终值 | I1: 终值现值 | J1: 总现值 | K1: 终值占比
A2: 0.2 | B2: =Inputs!B16*(1+A2)^1 -> 11.743866 | C2: =Inputs!B16*(1+A2)^2 -> 14.092639 | D2: =Inputs!B16*(1+A2)^3 -> 16.911166 | E2: =Inputs!B16*(1+A2)^4 -> 20.2934 | F2: =Inputs!B16*(1+A2)^5 -> 24.35208 | G2: =B2/(1+Inputs!B6)^1+C2/(1+Inputs!B6)^2+D2/(1+Inputs!B6)^3+E2/(1+Inputs!B6)^4+F2/(1+Inputs!B6)^5 -> 60.47204 | H2: =F2*(1+Inputs!B7)/(Inputs!B6-Inputs!B7) -> 316.57703 | I2: =H2/(1+Inputs!B6)^5 -> 179.63431 | J2: =G2+I2 -> 240.10635 | K2: =I2/J2 -> 0.74814477
A3: 0.3 | B3: =Inputs!B16*(1+A3)^1 -> 12.722521 | C3: =Inputs!B16*(1+A3)^2 -> 16.539277 | D3: =Inputs!B16*(1+A3)^3 -> 21.501061 | E3: =Inputs!B16*(1+A3)^4 -> 27.951379 | F3: =Inputs!B16*(1+A3)^5 -> 36.336792 | G3: =B3/(1+Inputs!B6)^1+C3/(1+Inputs!B6)^2+D3/(1+Inputs!B6)^3+E3/(1+Inputs!B6)^4+F3/(1+Inputs!B6)^5 -> 78.230513 | H3: =F3*(1+Inputs!B7)/(Inputs!B6-Inputs!B7) -> 472.3783 | I3: =H3/(1+Inputs!B6)^5 -> 268.04013 | J3: =G3+I3 -> 346.27065 | K3: =I3/J3 -> 0.77407697
A4: 0.4 | B4: =Inputs!B16*(1+A4)^1 -> 13.701176 | C4: =Inputs!B16*(1+A4)^2 -> 19.181647 | D4: =Inputs!B16*(1+A4)^3 -> 26.854306 | E4: =Inputs!B16*(1+A4)^4 -> 37.596028 | F4: =Inputs!B16*(1+A4)^5 -> 52.63444 | G4: =B4/(1+Inputs!B6)^1+C4/(1+Inputs!B6)^2+D4/(1+Inputs!B6)^3+E4/(1+Inputs!B6)^4+F4/(1+Inputs!B6)^5 -> 100.3982 | H4: =F4*(1+Inputs!B7)/(Inputs!B6-Inputs!B7) -> 684.24771 | I4: =H4/(1+Inputs!B6)^5 -> 388.26053 | J4: =G4+I4 -> 488.65873 | K4: =I4/J4 -> 0.79454332
A5: 这是简化股权DCF；起始值是单季度经济调整后年化代理，不是已实现年度所有者收益。
A6: 固定股数；现金流含利息；不重复扣净债务；未计额外担保损失或超额现金分配。
A7: 年增长率、折现率和永续增长率均为独立模型假设。

Sheet Sources
A1: 编号 | B1: 出版者与资料 | C1: 日期 | D1: 链接 | E1: 用途
A2: S1 | B2: Stock Analysis historical prices | C2: 2026-09-08 | D2: https://stockanalysis.com/stocks/avgo/history/ | E2: 报价
A3: S2 | B3: Stock Analysis overview | C3: 2026-09-09 accessed | D3: https://stockanalysis.com/stocks/avgo/ | E3: 股数与市值
A4: S3 | B4: Broadcom SEC Q3 exhibit 99.1 | C4: 2026-09-02 | D4: https://www.sec.gov/Archives/edgar/data/1730168/000173016826000076/avgo-08022026x8kxex99.htm | E4: 季度数据
A5: S4 | B5: Stock Analysis quarterly cash flows | C5: 2026-09-09 accessed | D5: https://stockanalysis.com/stocks/avgo/financials/cash-flow-statement/?p=quarterly | E5: TTM FCF
A6: S5 | B6: Stock Analysis forecast | C6: 2026-09-07 updated | D6: https://stockanalysis.com/stocks/avgo/forecast/ | E6: FY2026 EPS consensus
A7: S6 | B7: Benzinga Q3 call transcript | C7: 2026-09-02 call | D7: https://www.benzinga.com/news/26/09/61592658/broadcom-q3-2026-earnings-call-transcript | E7: 管理层AI展望
A8: 说明 | B8: 完整研究与风险来源见同目录报告 | E8: 数字模型假设不是公司指引或独立市场共识
